docs/conf.py
specter/__init__.py
specter/__main__.py
specter/expect.py
specter/parallel.py
specter/runner.py
specter/scanner.py
specter/spec.py
specter/util.py
specter/reporting/__init__.py
specter/reporting/console.py
specter/reporting/dots.py
specter/reporting/specter_json.py
specter/reporting/utils.py
specter/reporting/xunit.py
specter/vendor/__init__.py
specter/vendor/ast_decompiler.py
Specter-0.7.0.dist-info/LICENSE
Specter-0.7.0.dist-info/METADATA
Specter-0.7.0.dist-info/NOTICE
Specter-0.7.0.dist-info/WHEEL
Specter-0.7.0.dist-info/entry_points.txt
Specter-0.7.0.dist-info/top_level.txt
Specter-0.7.0.dist-info/RECORD
