Metadata-Version: 2.1
Name: Specter
Version: 0.7.0
Summary: Specter is a spec-based testing library to help facilitate BDD-testing in Python.
Author-email: John Vrbanac <john.vrbanac@linux.com>
License: MIT License
Project-URL: Homepage, https://github.com/jmvrbanac/Specter
Classifier: Development Status :: 4 - Beta
Classifier: Intended Audience :: Developers
Classifier: Natural Language :: English
Classifier: License :: OSI Approved :: MIT License
Classifier: Operating System :: POSIX :: Linux
Classifier: Programming Language :: Python
Classifier: Programming Language :: Python :: 3.7
Classifier: Programming Language :: Python :: 3.8
Classifier: Programming Language :: Python :: 3.9
Classifier: Programming Language :: Python :: 3.10
Classifier: Programming Language :: Python :: 3.11
Classifier: Programming Language :: Python :: 3.12
Requires-Python: >=3.7
License-File: LICENSE
License-File: NOTICE
Requires-Dist: pike >=0.2.0
Requires-Dist: pyevents
Requires-Dist: coverage
Provides-Extra: test
Requires-Dist: pytest ; extra == 'test'
Requires-Dist: flake8 ; extra == 'test'
